aonvif/__init__.py
aonvif/cli.py
aonvif/client.py
aonvif/exceptions.py
aonvif/wsdl/__init__.py
aonvif/wsdl/b-2.xsd
aonvif/wsdl/bf-2.xsd
aonvif/wsdl/include
aonvif/wsdl/soap-envelope
aonvif/wsdl/t-1.xsd
aonvif/wsdl/ws-addr.xsd
aonvif/wsdl/xml.xsd
aonvif/wsdl/xmlmime
aonvif/wsdl/ver10/actionengine.wsdl
aonvif/wsdl/ver10/analyticsdevice.wsdl
aonvif/wsdl/ver10/deviceio.wsdl
aonvif/wsdl/ver10/display.wsdl
aonvif/wsdl/ver10/federatedsearch.wsdl
aonvif/wsdl/ver10/receiver.wsdl
aonvif/wsdl/ver10/recording.wsdl
aonvif/wsdl/ver10/replay.wsdl
aonvif/wsdl/ver10/search.wsdl
aonvif/wsdl/ver10/accesscontrol/wsdl/index.html
aonvif/wsdl/ver10/accessrules/wsdl/accessrules.wsdl
aonvif/wsdl/ver10/accessrules/wsdl/index.html
aonvif/wsdl/ver10/advancedsecurity/wsdl/advancedsecurity.wsdl
aonvif/wsdl/ver10/advancedsecurity/wsdl/index.html
aonvif/wsdl/ver10/advancedsecurity/wsdl/security.wsdl
aonvif/wsdl/ver10/appmgmt/wsdl/appmgmt.wsdl
aonvif/wsdl/ver10/appmgmt/wsdl/index.html
aonvif/wsdl/ver10/authenticationbehavior/wsdl/authenticationbehavior.wsdl
aonvif/wsdl/ver10/authenticationbehavior/wsdl/index.html
aonvif/wsdl/ver10/credential/wsdl/credential.wsdl
aonvif/wsdl/ver10/credential/wsdl/index.html
aonvif/wsdl/ver10/device/wsdl/devicemgmt.wsdl
aonvif/wsdl/ver10/display/display.wsdl
aonvif/wsdl/ver10/display/wsdl/index.htm
aonvif/wsdl/ver10/doorcontrol/wsdl/index.html
aonvif/wsdl/ver10/events/wsdl/bw-2-vs-mod.wsdl
aonvif/wsdl/ver10/events/wsdl/event-vs.wsdl
aonvif/wsdl/ver10/events/wsdl/event.wsdl
aonvif/wsdl/ver10/events/wsdl/index.html
aonvif/wsdl/ver10/media/wsdl/media.wsdl
aonvif/wsdl/ver10/pacs/accesscontrol.wsdl
aonvif/wsdl/ver10/pacs/doorcontrol.wsdl
aonvif/wsdl/ver10/pacs/types.xsd
aonvif/wsdl/ver10/provisioning/wsdl/provisioning.wsdl
aonvif/wsdl/ver10/schedule/wsdl/index.html
aonvif/wsdl/ver10/schedule/wsdl/schedule.wsdl
aonvif/wsdl/ver10/schema/common.xsd
aonvif/wsdl/ver10/schema/metadatastream.xsd
aonvif/wsdl/ver10/schema/onvif.xsd
aonvif/wsdl/ver10/thermal/wsdl/index.html
aonvif-1.0.0rc8.dist-info/LICENSE
aonvif-1.0.0rc8.dist-info/METADATA
aonvif-1.0.0rc8.dist-info/WHEEL
aonvif-1.0.0rc8.dist-info/entry_points.txt
aonvif-1.0.0rc8.dist-info/top_level.txt
aonvif-1.0.0rc8.dist-info/RECORD
