Metadata-Version: 2.1
Name: aonvif
Version: 1.0.0rc8
Summary: ONVIF asynchronous client implementation in Python
Home-page: https://github.com/martyanov/aonvif
Author: Andrey Martyanov
Author-email: andrey@martyanov.com
License: MIT
Project-URL: Bug Reports, https://github.com/martyanov/aonvif/issues
Project-URL: Repository, https://github.com/martyanov/aonvif
Keywords: onvif,client,asyncio
Classifier: Development Status :: 3 - Alpha
Classifier: Intended Audience :: Developers
Classifier: License :: OSI Approved :: MIT License
Classifier: Programming Language :: Python :: 3
Classifier: Programming Language :: Python :: 3.9
Classifier: Programming Language :: Python :: 3.10
Classifier: Programming Language :: Python :: 3.11
Requires-Python: >=3.9.1,<4
License-File: LICENSE
Requires-Dist: zeep[async] (<5,>=4)
Provides-Extra: dev
Requires-Dist: flake8-bugbear (==22.10.27) ; extra == 'dev'
Requires-Dist: flake8-commas (==2.1.0) ; extra == 'dev'
Requires-Dist: flake8-comprehensions (==3.10.1) ; extra == 'dev'
Requires-Dist: flake8-isort (==5.0.3) ; extra == 'dev'
Requires-Dist: flake8 (==6.0.0) ; extra == 'dev'
Requires-Dist: pep8-naming (==0.13.2) ; extra == 'dev'
Requires-Dist: twine (==4.0.2) ; extra == 'dev'
Provides-Extra: test
Requires-Dist: pytest-asyncio (==0.20.2) ; extra == 'test'
Requires-Dist: pytest-cov (==4.0.0) ; extra == 'test'
Requires-Dist: pytest (==7.2.0) ; extra == 'test'
Requires-Dist: pytest-mock (==3.14.0) ; extra == 'test'
